fasttp.py
fasttp-0.0.1.dist-info/METADATA
fasttp-0.0.1.dist-info/WHEEL
fasttp-0.0.1.dist-info/top_level.txt
fasttp-0.0.1.dist-info/RECORD
